kibera/__init__.py
kibera/api.py
kibera/cli.py
kibera/core/__init__.py
kibera/core/logging.py
kibera/core/metrics.py
kibera/core/mongo.py
kibera/core/shell.py
kibera/keys.py
kibera/users.py
kibera-0.1.1.dist-info/entry_points.txt
kibera-0.1.1.dist-info/WHEEL
kibera-0.1.1.dist-info/METADATA
kibera-0.1.1.dist-info/RECORD
