Metadata-Version: 2.1
Name: kibera
Version: 0.1.1
Summary: 
Author: Hadi
Author-email: hadi.zolfaghaari@gmail.com
Requires-Python: >=3.8,<4.0
Classifier: Programming Language :: Python :: 3
Classifier: Programming Language :: Python :: 3.8
Classifier: Programming Language :: Python :: 3.9
Classifier: Programming Language :: Python :: 3.10
Classifier: Programming Language :: Python :: 3.11
Requires-Dist: flask (>=2.2.2,<3.0.0)
Requires-Dist: portforward (>=0.3.0,<0.4.0)
Requires-Dist: prometheus-client (>=0.15.0,<0.16.0)
Requires-Dist: pymongo (>=4.3.2,<5.0.0)
Requires-Dist: redis (>=3.5.3,<4.0.0)
Requires-Dist: rich (>=12.6.0,<13.0.0)
Requires-Dist: tqdm (>=4.60.0,<5.0.0)
Requires-Dist: waitress (>=2.1.2,<3.0.0)
